[[{"leg_id": "MOL000080", "type": "primary", "name": "Frederick, Keith", "+sponsor_link": "http://www.house.mo.govhttp://house.mo.gov/member.aspx?district=121&year=2016"}], "HB 1682", [{"leg_id": "MOL000415", "type": "primary", "name": "Hegeman", "+sponsor_link": "http://www.senate.mo.gov/16web/mem12"}], "SB 635", [{"leg_id": "MOL000110", "type": "primary", "name": "Koenig, Andrew", "+sponsor_link": "http://www.house.mo.govhttp://house.mo.gov/member.aspx?district=099&year=2016"}], "HB 1816", [{"leg_id": "MOL000157", "type": "primary", "name": "Sater", "+sponsor_link": "http://www.senate.mo.gov/16web/mem29"}], "SB 865", [{"leg_id": "MOL000033", "type": "primary", "name": "Wasson", "+sponsor_link": "http://www.senate.mo.gov/16web/mem20"}], "SB 973", [{"leg_id": "MOL000015", "type": "primary", "name": "Kraus", "+sponsor_link": "http://www.senate.mo.gov/16web/mem08"}], "SB 988", [{"leg_id": "MOL000402", "type": "primary", "name": "Alferman, Justin", "+sponsor_link": "http://www.house.mo.govhttp://house.mo.gov/member.aspx?district=061&year=2016"}], "HB 1851", [{"leg_id": "MOL000146", "type": "primary", "name": "Phillips, Don", "+sponsor_link": "http://www.house.mo.govhttp://house.mo.gov/member.aspx?district=138&year=2016"}], "HB 1599", [{"leg_id": "MOL000263", "type": "primary", "name": "Haahr, Elijah", "+sponsor_link": "http://www.house.mo.govhttp://house.mo.gov/member.aspx?district=134&year=2016"}], "HB 1649", [{"leg_id": "MOL000316", "type": "primary", "name": "Neely, Jim", "+sponsor_link": "http://www.house.mo.govhttp://house.mo.gov/member.aspx?district=008&year=2016"}], "HB 1550", [{"leg_id": "MOL000120", "type": "primary", "name": "Leara, Mike", "+sponsor_link": "http://www.house.mo.govhttp://house.mo.gov/member.aspx?district=096&year=2016"}], "HB 1561", [{"leg_id": "MOL000339", "type": "primary", "name": "Rowden, Caleb", "+sponsor_link": "http://www.house.mo.govhttp://house.mo.gov/member.aspx?district=044&year=2016"}], "HB 1698", [{"leg_id": "MOL000094", "type": "primary", "name": "Hoskins, Denny", "+sponsor_link": "http://www.house.mo.govhttp://house.mo.gov/member.aspx?district=054&year=2016"}], "HB 1870", [{"leg_id": "MOL000138", "type": "primary", "name": "Nasheed", "+sponsor_link": "http://www.senate.mo.gov/16web/mem05"}], "SB 833", [{"leg_id": "MOL000094", "type": "primary", "name": "Hoskins, Denny", "+sponsor_link": "http://www.house.mo.govhttp://house.mo.gov/member.aspx?district=054&year=2016"}], "HB 1976", [{"leg_id": "MOL000190", "type": "primary", "name": "Wieland", "+sponsor_link": "http://www.senate.mo.gov/16web/mem22"}], "SB 861", [{"leg_id": "MOL000153", "type": "primary", "name": "Riddle", "+sponsor_link": "http://www.senate.mo.gov/16web/mem10"}], "SB 921", [{"leg_id": "MOL000031", "type": "primary", "name": "Schmitt", "+sponsor_link": "http://www.senate.mo.gov/16web/mem15"}], "SB 919", [{"leg_id": "MOL000198", "type": "primary", "name": "Cunningham", "+sponsor_link": "http://www.senate.mo.gov/16web/mem33"}], "SB 932", [{"leg_id": "MOL000286", "type": "primary", "name": "Kolkmeyer, Glen", "+sponsor_link": "http://www.house.mo.govhttp://house.mo.gov/member.aspx?district=053&year=2016"}], "HB 2380", [{"leg_id": "MOL000095", "type": "primary", "name": "Hough, Lincoln", "+sponsor_link": "http://www.house.mo.govhttp://house.mo.gov/member.aspx?district=135&year=2016"}], "HB 2376", [{"leg_id": "MOL000100", "type": "primary", "name": "Johnson, Delus", "+sponsor_link": "http://www.house.mo.govhttp://house.mo.gov/member.aspx?district=009&year=2016"}], "HB 2453", [{"leg_id": "MOL000324", "type": "primary", "name": "Pfautsch, Donna", "+sponsor_link": "http://www.house.mo.govhttp://house.mo.gov/member.aspx?district=033&year=2016"}], "HB 1418", [{"leg_id": "MOL000110", "type": "primary", "name": "Koenig, Andrew", "+sponsor_link": "http://www.house.mo.govhttp://house.mo.gov/member.aspx?district=099&year=2016"}], "HB 1434", [{"leg_id": "MOL000415", "type": "primary", "name": "Hegeman", "+sponsor_link": "http://www.senate.mo.gov/16web/mem12"}], "SB 1002", [{"leg_id": "MOL000183", "type": "primary", "name": "Wallingford", "+sponsor_link": "http://www.senate.mo.gov/16web/mem27"}, {"leg_id": "MOL000024", "type": "cosponsor", "name": "David Pearce", "+sponsor_link": "http://www.senate.mo.gov/16web/mem21"}, {"leg_id": "MOL000015", "type": "cosponsor", "name": "Will Kraus", "+sponsor_link": "http://www.senate.mo.gov/16web/mem08"}], "SB 814", [{"leg_id": "MOL000121", "type": "primary", "name": "Lichtenegger, Donna", "+sponsor_link": "http://www.house.mo.govhttp://house.mo.gov/member.aspx?district=146&year=2016"}], "HB 1717", [{"leg_id": "MOL000015", "type": "primary", "name": "Kraus", "+sponsor_link": "http://www.senate.mo.gov/16web/mem08"}], "SB 823", [{"leg_id": "MOL000392", "type": "primary", "name": "Vescovo, Rob", "+sponsor_link": "http://www.house.mo.govhttp://house.mo.gov/member.aspx?district=112&year=2016"}], "HB 1432", [{"leg_id": "MOL000110", "type": "primary", "name": "Koenig, Andrew", "+sponsor_link": "http://www.house.mo.govhttp://house.mo.gov/member.aspx?district=099&year=2016"}], "HB 1435", [{"leg_id": "MOL000332", "type": "primary", "name": "Remole, Tim", "+sponsor_link": "http://www.house.mo.govhttp://house.mo.gov/member.aspx?district=006&year=2016"}], "HB 1713", [{"leg_id": "MOL000183", "type": "primary", "name": "Wallingford", "+sponsor_link": "http://www.senate.mo.gov/16web/mem27"}], "SB 794", [{"leg_id": "MOL000106", "type": "primary", "name": "Kelley, Mike", "+sponsor_link": "http://www.house.mo.govhttp://house.mo.gov/member.aspx?district=127&year=2016"}], "HB 1582", [{"leg_id": "MOL000094", "type": "primary", "name": "Hoskins, Denny", "+sponsor_link": "http://www.house.mo.govhttp://house.mo.gov/member.aspx?district=054&year=2016"}], "HB 2030", [{"leg_id": "MOL000150", "type": "primary", "name": "Redmon, Craig", "+sponsor_link": "http://www.house.mo.govhttp://house.mo.gov/member.aspx?district=004&year=2016"}], "HB 2381", [{"leg_id": "MOL000021", "type": "primary", "name": "Munzlinger", "+sponsor_link": "http://www.senate.mo.gov/16web/mem18"}], "SB 655", [{"leg_id": "MOL000021", "type": "primary", "name": "Munzlinger", "+sponsor_link": "http://www.senate.mo.gov/16web/mem18"}], "SB 657", [{"leg_id": "MOL000023", "type": "primary", "name": "Parson", "+sponsor_link": "http://www.senate.mo.gov/16web/mem28"}], "SB 664", [{"leg_id": "MOL000023", "type": "primary", "name": "Parson", "+sponsor_link": "http://www.senate.mo.gov/16web/mem28"}], "SB 665", [{"leg_id": "MOL000030", "type": "primary", "name": "Schaefer", "+sponsor_link": "http://www.senate.mo.gov/16web/mem19"}], "SB 915", [{"leg_id": "MOL000096", "type": "primary", "name": "Houghton, Jay", "+sponsor_link": "http://www.house.mo.govhttp://house.mo.gov/member.aspx?district=043&year=2016"}], "HB 2335", [{"leg_id": "MOL000153", "type": "primary", "name": "Riddle", "+sponsor_link": "http://www.senate.mo.gov/16web/mem10"}], "SB 1009", [{"leg_id": "MOL000152", "type": "primary", "name": "Richardson, Todd", "+sponsor_link": "http://www.house.mo.govhttp://house.mo.gov/member.aspx?district=152&year=2016"}], "HB 2591", [{"leg_id": "MOL000094", "type": "primary", "name": "Hoskins, Denny", "+sponsor_link": "http://www.house.mo.govhttp://house.mo.gov/member.aspx?district=054&year=2016"}], "HB 2194", [{"leg_id": "MOL000023", "type": "primary", "name": "Parson", "+sponsor_link": "http://www.senate.mo.gov/16web/mem28"}], "SB 947", [{"leg_id": "MOL000355", "type": "primary", "name": "Swan, Kathryn", "+sponsor_link": "http://www.house.mo.govhttp://house.mo.gov/member.aspx?district=147&year=2016"}], "HB 1646", [{"leg_id": "MOL000263", "type": "primary", "name": "Haahr, Elijah", "+sponsor_link": "http://www.house.mo.govhttp://house.mo.gov/member.aspx?district=134&year=2016"}], "HB 1562", [{"leg_id": "MOL000153", "type": "primary", "name": "Riddle", "+sponsor_link": "http://www.senate.mo.gov/16web/mem10"}, {"leg_id": "MOL000169", "type": "cosponsor", "name": "Ryan Silvey", "+sponsor_link": "http://www.senate.mo.gov/16web/mem17"}], "SB 638", [{"leg_id": "MOL000355", "type": "primary", "name": "Swan, Kathryn", "+sponsor_link": "http://www.house.mo.govhttp://house.mo.gov/member.aspx?district=147&year=2016"}], "HB 2379", [{"leg_id": "MOL000295", "type": "primary", "name": "Lynch, Steve", "+sponsor_link": "http://www.house.mo.govhttp://house.mo.gov/member.aspx?district=122&year=2016"}], "HB 1568", [{"leg_id": "MOL000387", "type": "primary", "name": "Fitzwater, Travis", "+sponsor_link": "http://www.house.mo.govhttp://house.mo.gov/member.aspx?district=049&year=2016"}], "HB 1684", [{"leg_id": "MOL000031", "type": "primary", "name": "Schmitt", "+sponsor_link": "http://www.senate.mo.gov/16web/mem15"}], "SB 572", [{"leg_id": "MOL000001", "type": "primary", "name": "Brown", "+sponsor_link": "http://www.senate.mo.gov/16web/mem16"}], "SB 986", [{"leg_id": "MOL000024", "type": "primary", "name": "Pearce", "+sponsor_link": "http://www.senate.mo.gov/16web/mem21"}], "SB 997", [{"leg_id": "MOL000076", "type": "primary", "name": "Flanigan, Tom", "+sponsor_link": "http://www.house.mo.govhttp://house.mo.gov/member.aspx?district=163&year=2016"}], "HB 2018", [{"leg_id": "MOL000076", "type": "primary", "name": "Flanigan, Tom", "+sponsor_link": "http://www.house.mo.govhttp://house.mo.gov/member.aspx?district=163&year=2016"}], "HB 2017", [{"leg_id": "MOL000366", "type": "primary", "name": "Wood, David", "+sponsor_link": "http://www.house.mo.govhttp://house.mo.gov/member.aspx?district=058&year=2016"}], "HB 1877", [{"leg_id": "MOL000168", "type": "primary", "name": "Sifton", "+sponsor_link": "http://www.senate.mo.gov/16web/mem01"}], "SB 905", [{"leg_id": "MOL000115", "type": "primary", "name": "Lant, Bill", "+sponsor_link": "http://www.house.mo.govhttp://house.mo.gov/member.aspx?district=159&year=2016"}], "HB 2355", [{"leg_id": "MOL000001", "type": "primary", "name": "Brown", "+sponsor_link": "http://www.senate.mo.gov/16web/mem16"}], "SB 711", [{"leg_id": "MOL000155", "type": "primary", "name": "Rowland, Lyle", "+sponsor_link": "http://www.house.mo.govhttp://house.mo.gov/member.aspx?district=155&year=2016"}], "HB 1696", [{"leg_id": "MOL000393", "type": "primary", "name": "Wiemann, John", "+sponsor_link": "http://www.house.mo.govhttp://house.mo.gov/member.aspx?district=103&year=2016"}], "HB 2150", [{"leg_id": "MOL000263", "type": "primary", "name": "Haahr, Elijah", "+sponsor_link": "http://www.house.mo.govhttp://house.mo.gov/member.aspx?district=134&year=2016"}], "HB 1681", [{"leg_id": "MOL000205", "type": "primary", "name": "Romine", "+sponsor_link": "http://www.senate.mo.gov/16web/mem03"}], "SB 620", [{"leg_id": "MOL000387", "type": "primary", "name": "Fitzwater, Travis", "+sponsor_link": "http://www.house.mo.govhttp://house.mo.gov/member.aspx?district=049&year=2016"}], "HB 2125", [{"leg_id": "MOL000001", "type": "primary", "name": "Brown", "+sponsor_link": "http://www.senate.mo.gov/16web/mem16"}], "SB 968", [{"leg_id": "MOL000355", "type": "primary", "name": "Swan, Kathryn", "+sponsor_link": "http://www.house.mo.govhttp://house.mo.gov/member.aspx?district=147&year=2016"}], "HB 2428", [{"leg_id": "MOL000248", "type": "primary", "name": "Fitzpatrick, Scott", "+sponsor_link": "http://www.house.mo.govhttp://house.mo.gov/member.aspx?district=158&year=2016"}], "HB 1941", [{"leg_id": "MOL000009", "type": "primary", "name": "Engler, Kevin", "+sponsor_link": "http://www.house.mo.govhttp://house.mo.gov/member.aspx?district=116&year=2016"}], "HB 1565", [{"leg_id": "MOL000076", "type": "primary", "name": "Flanigan, Tom", "+sponsor_link": "http://www.house.mo.govhttp://house.mo.gov/member.aspx?district=163&year=2016"}], "HB 1534", [{"leg_id": "MOL000029", "type": "primary", "name": "Schaaf", "+sponsor_link": "http://www.senate.mo.gov/16web/mem34"}, {"leg_id": "MOL000001", "type": "cosponsor", "name": "Dan Brown", "+sponsor_link": "http://www.senate.mo.gov/16web/mem16"}, {"leg_id": "MOL000417", "type": "cosponsor", "name": "Bob Onder", "+sponsor_link": "http://www.senate.mo.gov/16web/mem02"}], "SB 579", [{"leg_id": "MOL000094", "type": "primary", "name": "Hoskins, Denny", "+sponsor_link": "http://www.house.mo.govhttp://house.mo.gov/member.aspx?district=054&year=2016"}], "HB 2029", [{"leg_id": "MOL000030", "type": "primary", "name": "Schaefer", "+sponsor_link": "http://www.senate.mo.gov/16web/mem19"}], "SB 875", [{"leg_id": "MOL000061", "type": "primary", "name": "Crawford, Sandy", "+sponsor_link": "http://www.house.mo.govhttp://house.mo.gov/member.aspx?district=129&year=2016"}], "HB 1593", [{"leg_id": "MOL000120", "type": "primary", "name": "Leara, Mike", "+sponsor_link": "http://www.house.mo.govhttp://house.mo.gov/member.aspx?district=096&year=2016"}], "HB 1443", [{"leg_id": "MOL000202", "type": "primary", "name": "Libla", "+sponsor_link": "http://www.senate.mo.gov/16web/mem25"}], "SB 624", [{"leg_id": "MOL000033", "type": "primary", "name": "Wasson", "+sponsor_link": "http://www.senate.mo.gov/16web/mem20"}], "SB 660", [{"leg_id": "MOL000169", "type": "primary", "name": "Silvey", "+sponsor_link": "http://www.senate.mo.gov/16web/mem17"}, {"leg_id": "MOL000210", "type": "cosponsor", "name": "Gina Walsh", "+sponsor_link": "http://www.senate.mo.gov/16web/mem13"}, {"leg_id": "MOL000138", "type": "cosponsor", "name": "Jamilah Nasheed", "+sponsor_link": "http://www.senate.mo.gov/16web/mem05"}], "SB 838", [{"leg_id": "MOL000049", "type": "primary", "name": "Brown, Wanda", "+sponsor_link": "http://www.house.mo.govhttp://house.mo.gov/member.aspx?district=057&year=2016"}], "HB 1530", [{"leg_id": "MOL000069", "type": "primary", "name": "Dugger, Tony", "+sponsor_link": "http://www.house.mo.govhttp://house.mo.gov/member.aspx?district=141&year=2016"}], "HB 1721", [{"leg_id": "MOL000035", "type": "primary", "name": "Allen, Sue", "+sponsor_link": "http://www.house.mo.govhttp://house.mo.gov/member.aspx?district=100&year=2016"}], "HB 1583", [{"leg_id": "MOL000339", "type": "primary", "name": "Rowden, Caleb", "+sponsor_link": "http://www.house.mo.govhttp://house.mo.gov/member.aspx?district=044&year=2016"}], "HB 1979", [{"leg_id": "MOL000094", "type": "primary", "name": "Hoskins, Denny", "+sponsor_link": "http://www.house.mo.govhttp://house.mo.gov/member.aspx?district=054&year=2016"}], "HB 2140", [{"leg_id": "MOL000041", "type": "primary", "name": "Barnes, Jay", "+sponsor_link": "http://www.house.mo.govhttp://house.mo.gov/member.aspx?district=060&year=2016"}], "HB 2203", [{"leg_id": "MOL000076", "type": "primary", "name": "Flanigan, Tom", "+sponsor_link": "http://www.house.mo.govhttp://house.mo.gov/member.aspx?district=163&year=2016"}], "HB 2011", [{"leg_id": "MOL000248", "type": "primary", "name": "Fitzpatrick, Scott", "+sponsor_link": "http://www.house.mo.govhttp://house.mo.gov/member.aspx?district=158&year=2016"}], "HB 2006", [{"leg_id": "MOL000248", "type": "primary", "name": "Fitzpatrick, Scott", "+sponsor_link": "http://www.house.mo.govhttp://house.mo.gov/member.aspx?district=158&year=2016"}], "HB 2003", [{"leg_id": "MOL000248", "type": "primary", "name": "Fitzpatrick, Scott", "+sponsor_link": "http://www.house.mo.govhttp://house.mo.gov/member.aspx?district=158&year=2016"}], "HB 2004", [{"leg_id": "MOL000248", "type": "primary", "name": "Fitzpatrick, Scott", "+sponsor_link": "http://www.house.mo.govhttp://house.mo.gov/member.aspx?district=158&year=2016"}], "HB 2009", [{"leg_id": "MOL000248", "type": "primary", "name": "Fitzpatrick, Scott", "+sponsor_link": "http://www.house.mo.govhttp://house.mo.gov/member.aspx?district=158&year=2016"}], "HB 2005", [{"leg_id": "MOL000248", "type": "primary", "name": "Fitzpatrick, Scott", "+sponsor_link": "http://www.house.mo.govhttp://house.mo.gov/member.aspx?district=158&year=2016"}], "HB 2002", [{"leg_id": "MOL000248", "type": "primary", "name": "Fitzpatrick, Scott", "+sponsor_link": "http://www.house.mo.govhttp://house.mo.gov/member.aspx?district=158&year=2016"}], "HB 2010", [{"leg_id": "MOL000248", "type": "primary", "name": "Fitzpatrick, Scott", "+sponsor_link": "http://www.house.mo.govhttp://house.mo.gov/member.aspx?district=158&year=2016"}], "HB 2012", [{"leg_id": "MOL000076", "type": "primary", "name": "Flanigan, Tom", "+sponsor_link": "http://www.house.mo.govhttp://house.mo.gov/member.aspx?district=163&year=2016"}], "HB 2013", [{"leg_id": "MOL000248", "type": "primary", "name": "Fitzpatrick, Scott", "+sponsor_link": "http://www.house.mo.govhttp://house.mo.gov/member.aspx?district=158&year=2016"}], "HB 2007", [{"leg_id": "MOL000076", "type": "primary", "name": "Flanigan, Tom", "+sponsor_link": "http://www.house.mo.govhttp://house.mo.gov/member.aspx?district=163&year=2016"}], "HB 2008", [{"leg_id": "MOL000076", "type": "primary", "name": "Flanigan, Tom", "+sponsor_link": "http://www.house.mo.govhttp://house.mo.gov/member.aspx?district=163&year=2016"}], "HB 2001", [{"leg_id": "MOL000248", "type": "primary", "name": "Fitzpatrick, Scott", "+sponsor_link": "http://www.house.mo.govhttp://house.mo.gov/member.aspx?district=158&year=2016"}], "HB 2014", [{"leg_id": "MOL000033", "type": "primary", "name": "Wasson", "+sponsor_link": "http://www.senate.mo.gov/16web/mem20"}], "SB 586", [{"leg_id": "MOL000391", "type": "primary", "name": "Dogan, Shamed", "+sponsor_link": "http://www.house.mo.govhttp://house.mo.gov/member.aspx?district=098&year=2016"}], "HB 1983", [{"leg_id": "MOL000033", "type": "primary", "name": "Wasson", "+sponsor_link": "http://www.senate.mo.gov/16web/mem20"}, {"leg_id": "MOL000157", "type": "cosponsor", "name": "David Sater", "+sponsor_link": "http://www.senate.mo.gov/16web/mem29"}], "SB 585"]